baem200/__init__.py
baem200/m1com.py
baem200/m1comTest.py
baem200/mconfig.py
baem200/utils.py
baem200-0.0.13.dist-info/LICENCE
baem200-0.0.13.dist-info/METADATA
baem200-0.0.13.dist-info/WHEEL
baem200-0.0.13.dist-info/top_level.txt
baem200-0.0.13.dist-info/RECORD
