Metadata-Version: 2.1
Name: baem200
Version: 0.0.13
Summary: Bachmann electronic Python Util Library
Home-page: https://github.com/bachmann-m200/baem200
Author: Sven Neumann
Author-email: sven.neumann@bachmann.info
Classifier: Programming Language :: Python :: 3
Classifier: License :: Other/Proprietary License
Classifier: Operating System :: Microsoft :: Windows :: Windows 10
License-File: LICENCE
